myfunctions_NazymSmagulova/__init__.py
myfunctions_NazymSmagulova/math.py
myfunctions_NazymSmagulova-0.0.1.dist-info/METADATA
myfunctions_NazymSmagulova-0.0.1.dist-info/WHEEL
myfunctions_NazymSmagulova-0.0.1.dist-info/top_level.txt
myfunctions_NazymSmagulova-0.0.1.dist-info/RECORD
