Metadata-Version: 2.1
Name: myfunctions-NazymSmagulova
Version: 0.0.1
Summary: A description of your package
Home-page: UNKNOWN
Author: Smagulova
Author-email: 
License: https://github.com/NazymSmagulova/
Platform: UNKNOWN
Classifier: Programming Language :: Python :: 3
Classifier: License :: OSI Approved :: MIT License
Classifier: Operating System :: OS Independent
Requires-Python: >=3.6
